samkit/__init__.py
samkit/main.py
samkit/ss_reader.py
sam_kit-1.0.1.dist-info/LICENSE.md
sam_kit-1.0.1.dist-info/METADATA
sam_kit-1.0.1.dist-info/WHEEL
sam_kit-1.0.1.dist-info/top_level.txt
sam_kit-1.0.1.dist-info/RECORD
